cynonblockingsubprocess/LICENSE
cynonblockingsubprocess/README.MD
cynonblockingsubprocess/__init__.py
cynonblockingsubprocess/nonblockingsubprocess.hpp
cynonblockingsubprocess/requirements.txt
cynonblockingsubprocess/thirdparty.json
cynonblockingsubprocess/uiev.pyx
cynonblockingsubprocess/uiev_compile.py
cynonblockingsubprocess-0.10.dist-info/LICENSE.rst
cynonblockingsubprocess-0.10.dist-info/METADATA
cynonblockingsubprocess-0.10.dist-info/WHEEL
cynonblockingsubprocess-0.10.dist-info/top_level.txt
cynonblockingsubprocess-0.10.dist-info/RECORD
