Metadata-Version: 2.1
Name: cynonblockingsubprocess
Version: 0.10
Summary: Nogil subprocess for Python with stdout/stderr capturing and stdin writing - without deadlocking!
Home-page: https://github.com/hansalemaos/cynonblockingsubprocess
Author: Johannes Fischer
Author-email: aulasparticularesdealemaosp@gmail.com
License: MIT
Keywords: subprocess,Cython,c++,nogil,nonblocking
Classifier: Development Status :: 4 - Beta
Classifier: Programming Language :: Python :: 3 :: Only
Classifier: Programming Language :: Python :: 3.10
Classifier: Topic :: Software Development :: Libraries :: Python Modules
Classifier: Topic :: Utilities
License-File: LICENSE.rst
Requires-Dist: Cython
Requires-Dist: setuptools
